{"loss": 8.47860865178518e-05, "accuracy": -3.4568675700639977, "time_this_iter_s": 0.20200324058532715, "done": false, "timesteps_total": null, "episodes_total": null, "training_iteration": 1, "experiment_id": "1f230671e13a48cc8b223fcc9e459d59", "date": "2020-12-22_12-40-33", "timestamp": 1608669633, "time_total_s": 0.20200324058532715, "pid": 50076, "hostname": "DESKTOP-L6D69LH", "node_ip": "192.168.1.102", "config": {"num_neurons": 64, "num_hidden": 3, "activation_fn": "<function relu at 0x0000019253FF49D8>", "lr": 0.0012225396885064191}, "time_since_restore": 0.20200324058532715, "timesteps_since_restore": 0, "iterations_since_restore": 1, "trial_id": "e7ced5ec", "experiment_tag": "2_activation_fn=<function relu at 0x0000019253FF49D8>,lr=0.0012225,num_hidden=3,num_neurons=64"}
{"loss": 2.8289799047342967e-05, "accuracy": -0.48946702949954557, "time_this_iter_s": 0.22099852561950684, "done": false, "timesteps_total": null, "episodes_total": null, "training_iteration": 2, "experiment_id": "1f230671e13a48cc8b223fcc9e459d59", "date": "2020-12-22_12-40-33", "timestamp": 1608669633, "time_total_s": 0.423001766204834, "pid": 50076, "hostname": "DESKTOP-L6D69LH", "node_ip": "192.168.1.102", "config": {"num_neurons": 64, "num_hidden": 3, "activation_fn": "<function relu at 0x0000019253FF49D8>", "lr": 0.0012225396885064191}, "time_since_restore": 0.423001766204834, "timesteps_since_restore": 0, "iterations_since_restore": 2, "trial_id": "e7ced5ec", "experiment_tag": "2_activation_fn=<function relu at 0x0000019253FF49D8>,lr=0.0012225,num_hidden=3,num_neurons=64"}
{"loss": 1.8541646568337455e-05, "accuracy": -0.006721890584090451, "time_this_iter_s": 0.19899821281433105, "done": false, "timesteps_total": null, "episodes_total": null, "training_iteration": 3, "experiment_id": "1f230671e13a48cc8b223fcc9e459d59", "date": "2020-12-22_12-40-33", "timestamp": 1608669633, "time_total_s": 0.621999979019165, "pid": 50076, "hostname": "DESKTOP-L6D69LH", "node_ip": "192.168.1.102", "config": {"num_neurons": 64, "num_hidden": 3, "activation_fn": "<function relu at 0x0000019253FF49D8>", "lr": 0.0012225396885064191}, "time_since_restore": 0.621999979019165, "timesteps_since_restore": 0, "iterations_since_restore": 3, "trial_id": "e7ced5ec", "experiment_tag": "2_activation_fn=<function relu at 0x0000019253FF49D8>,lr=0.0012225,num_hidden=3,num_neurons=64"}
{"loss": 2.062053590634605e-05, "accuracy": -0.06355003447630359, "time_this_iter_s": 0.1780102252960205, "done": false, "timesteps_total": null, "episodes_total": null, "training_iteration": 4, "experiment_id": "1f230671e13a48cc8b223fcc9e459d59", "date": "2020-12-22_12-40-33", "timestamp": 1608669633, "time_total_s": 0.8000102043151855, "pid": 50076, "hostname": "DESKTOP-L6D69LH", "node_ip": "192.168.1.102", "config": {"num_neurons": 64, "num_hidden": 3, "activation_fn": "<function relu at 0x0000019253FF49D8>", "lr": 0.0012225396885064191}, "time_since_restore": 0.8000102043151855, "timesteps_since_restore": 0, "iterations_since_restore": 4, "trial_id": "e7ced5ec", "experiment_tag": "2_activation_fn=<function relu at 0x0000019253FF49D8>,lr=0.0012225,num_hidden=3,num_neurons=64"}
{"loss": 2.209663489338709e-05, "accuracy": -0.16309331806556604, "time_this_iter_s": 0.1819925308227539, "done": false, "timesteps_total": null, "episodes_total": null, "training_iteration": 5, "experiment_id": "1f230671e13a48cc8b223fcc9e459d59", "date": "2020-12-22_12-40-34", "timestamp": 1608669634, "time_total_s": 0.9820027351379395, "pid": 50076, "hostname": "DESKTOP-L6D69LH", "node_ip": "192.168.1.102", "config": {"num_neurons": 64, "num_hidden": 3, "activation_fn": "<function relu at 0x0000019253FF49D8>", "lr": 0.0012225396885064191}, "time_since_restore": 0.9820027351379395, "timesteps_since_restore": 0, "iterations_since_restore": 5, "trial_id": "e7ced5ec", "experiment_tag": "2_activation_fn=<function relu at 0x0000019253FF49D8>,lr=0.0012225,num_hidden=3,num_neurons=64"}
{"loss": 2.096773823723197e-05, "accuracy": -0.07805002604359035, "time_this_iter_s": 0.17599272727966309, "done": false, "timesteps_total": null, "episodes_total": null, "training_iteration": 6, "experiment_id": "1f230671e13a48cc8b223fcc9e459d59", "date": "2020-12-22_12-40-34", "timestamp": 1608669634, "time_total_s": 1.1579954624176025, "pid": 50076, "hostname": "DESKTOP-L6D69LH", "node_ip": "192.168.1.102", "config": {"num_neurons": 64, "num_hidden": 3, "activation_fn": "<function relu at 0x0000019253FF49D8>", "lr": 0.0012225396885064191}, "time_since_restore": 1.1579954624176025, "timesteps_since_restore": 0, "iterations_since_restore": 6, "trial_id": "e7ced5ec", "experiment_tag": "2_activation_fn=<function relu at 0x0000019253FF49D8>,lr=0.0012225,num_hidden=3,num_neurons=64"}
{"loss": 1.9045901353820227e-05, "accuracy": 0.0028838600401984715, "time_this_iter_s": 0.15200376510620117, "done": false, "timesteps_total": null, "episodes_total": null, "training_iteration": 7, "experiment_id": "1f230671e13a48cc8b223fcc9e459d59", "date": "2020-12-22_12-40-34", "timestamp": 1608669634, "time_total_s": 1.3099992275238037, "pid": 50076, "hostname": "DESKTOP-L6D69LH", "node_ip": "192.168.1.102", "config": {"num_neurons": 64, "num_hidden": 3, "activation_fn": "<function relu at 0x0000019253FF49D8>", "lr": 0.0012225396885064191}, "time_since_restore": 1.3099992275238037, "timesteps_since_restore": 0, "iterations_since_restore": 7, "trial_id": "e7ced5ec", "experiment_tag": "2_activation_fn=<function relu at 0x0000019253FF49D8>,lr=0.0012225,num_hidden=3,num_neurons=64"}
{"loss": 1.8054373867926188e-05, "accuracy": 0.001352848982028143, "time_this_iter_s": 0.15599846839904785, "done": false, "timesteps_total": null, "episodes_total": null, "training_iteration": 8, "experiment_id": "1f230671e13a48cc8b223fcc9e459d59", "date": "2020-12-22_12-40-34", "timestamp": 1608669634, "time_total_s": 1.4659976959228516, "pid": 50076, "hostname": "DESKTOP-L6D69LH", "node_ip": "192.168.1.102", "config": {"num_neurons": 64, "num_hidden": 3, "activation_fn": "<function relu at 0x0000019253FF49D8>", "lr": 0.0012225396885064191}, "time_since_restore": 1.4659976959228516, "timesteps_since_restore": 0, "iterations_since_restore": 8, "trial_id": "e7ced5ec", "experiment_tag": "2_activation_fn=<function relu at 0x0000019253FF49D8>,lr=0.0012225,num_hidden=3,num_neurons=64"}
{"loss": 1.8192567495134426e-05, "accuracy": -0.015425291590335455, "time_this_iter_s": 0.16401052474975586, "done": false, "timesteps_total": null, "episodes_total": null, "training_iteration": 9, "experiment_id": "1f230671e13a48cc8b223fcc9e459d59", "date": "2020-12-22_12-40-34", "timestamp": 1608669634, "time_total_s": 1.6300082206726074, "pid": 50076, "hostname": "DESKTOP-L6D69LH", "node_ip": "192.168.1.102", "config": {"num_neurons": 64, "num_hidden": 3, "activation_fn": "<function relu at 0x0000019253FF49D8>", "lr": 0.0012225396885064191}, "time_since_restore": 1.6300082206726074, "timesteps_since_restore": 0, "iterations_since_restore": 9, "trial_id": "e7ced5ec", "experiment_tag": "2_activation_fn=<function relu at 0x0000019253FF49D8>,lr=0.0012225,num_hidden=3,num_neurons=64"}
{"loss": 2.3486378267989494e-05, "accuracy": -0.25312435415035495, "time_this_iter_s": 0.15198993682861328, "done": true, "timesteps_total": null, "episodes_total": null, "training_iteration": 10, "experiment_id": "1f230671e13a48cc8b223fcc9e459d59", "date": "2020-12-22_12-40-34", "timestamp": 1608669634, "time_total_s": 1.7819981575012207, "pid": 50076, "hostname": "DESKTOP-L6D69LH", "node_ip": "192.168.1.102", "config": {"num_neurons": 64, "num_hidden": 3, "activation_fn": "<function relu at 0x0000019253FF49D8>", "lr": 0.0012225396885064191}, "time_since_restore": 1.7819981575012207, "timesteps_since_restore": 0, "iterations_since_restore": 10, "trial_id": "e7ced5ec", "experiment_tag": "2_activation_fn=<function relu at 0x0000019253FF49D8>,lr=0.0012225,num_hidden=3,num_neurons=64"}
