{"loss": 0.0042972019873559475, "accuracy": -418.9850009050824, "time_this_iter_s": 0.7520008087158203, "should_checkpoint": true, "done": false, "timesteps_total": null, "episodes_total": null, "training_iteration": 1, "experiment_id": "6d99919bd69c4af2838902e6b6bbf8d5", "date": "2020-12-22_00-15-46", "timestamp": 1608624946, "time_total_s": 0.7520008087158203, "pid": 52920, "hostname": "DESKTOP-L6D69LH", "node_ip": "192.168.1.102", "config": {"num_neurons": 32, "num_hidden": 3, "activation_fn": "<function relu at 0x000001BAC2C4A8B8>", "lr": 0.00014124140190214133}, "time_since_restore": 0.7520008087158203, "timesteps_since_restore": 0, "iterations_since_restore": 1, "trial_id": "e0e28a86", "experiment_tag": "2_activation_fn=<function relu at 0x000001BAC2C4A8B8>,lr=0.00014124,num_hidden=3,num_neurons=32"}
{"loss": 0.003176918253302574, "accuracy": -309.4945653408479, "time_this_iter_s": 0.16500282287597656, "should_checkpoint": true, "done": false, "timesteps_total": null, "episodes_total": null, "training_iteration": 2, "experiment_id": "6d99919bd69c4af2838902e6b6bbf8d5", "date": "2020-12-22_00-15-46", "timestamp": 1608624946, "time_total_s": 0.9170036315917969, "pid": 52920, "hostname": "DESKTOP-L6D69LH", "node_ip": "192.168.1.102", "config": {"num_neurons": 32, "num_hidden": 3, "activation_fn": "<function relu at 0x000001BAC2C4A8B8>", "lr": 0.00014124140190214133}, "time_since_restore": 0.9170036315917969, "timesteps_since_restore": 0, "iterations_since_restore": 2, "trial_id": "e0e28a86", "experiment_tag": "2_activation_fn=<function relu at 0x000001BAC2C4A8B8>,lr=0.00014124,num_hidden=3,num_neurons=32"}
{"loss": 0.002310368465259671, "accuracy": -224.80279335996474, "time_this_iter_s": 0.2200031280517578, "should_checkpoint": true, "done": false, "timesteps_total": null, "episodes_total": null, "training_iteration": 3, "experiment_id": "6d99919bd69c4af2838902e6b6bbf8d5", "date": "2020-12-22_00-15-46", "timestamp": 1608624946, "time_total_s": 1.1370067596435547, "pid": 52920, "hostname": "DESKTOP-L6D69LH", "node_ip": "192.168.1.102", "config": {"num_neurons": 32, "num_hidden": 3, "activation_fn": "<function relu at 0x000001BAC2C4A8B8>", "lr": 0.00014124140190214133}, "time_since_restore": 1.1370067596435547, "timesteps_since_restore": 0, "iterations_since_restore": 3, "trial_id": "e0e28a86", "experiment_tag": "2_activation_fn=<function relu at 0x000001BAC2C4A8B8>,lr=0.00014124,num_hidden=3,num_neurons=32"}
{"loss": 0.0016041788039729, "accuracy": -155.7836521882612, "time_this_iter_s": 1.1598656177520752, "should_checkpoint": true, "done": false, "timesteps_total": null, "episodes_total": null, "training_iteration": 4, "experiment_id": "6d99919bd69c4af2838902e6b6bbf8d5", "date": "2020-12-22_00-15-48", "timestamp": 1608624948, "time_total_s": 2.29687237739563, "pid": 52920, "hostname": "DESKTOP-L6D69LH", "node_ip": "192.168.1.102", "config": {"num_neurons": 32, "num_hidden": 3, "activation_fn": "<function relu at 0x000001BAC2C4A8B8>", "lr": 0.00014124140190214133}, "time_since_restore": 2.29687237739563, "timesteps_since_restore": 0, "iterations_since_restore": 4, "trial_id": "e0e28a86", "experiment_tag": "2_activation_fn=<function relu at 0x000001BAC2C4A8B8>,lr=0.00014124,num_hidden=3,num_neurons=32"}
{"loss": 0.0010583476396277547, "accuracy": -102.43711942569955, "time_this_iter_s": 0.9519975185394287, "should_checkpoint": true, "done": false, "timesteps_total": null, "episodes_total": null, "training_iteration": 5, "experiment_id": "6d99919bd69c4af2838902e6b6bbf8d5", "date": "2020-12-22_00-15-49", "timestamp": 1608624949, "time_total_s": 3.2488698959350586, "pid": 52920, "hostname": "DESKTOP-L6D69LH", "node_ip": "192.168.1.102", "config": {"num_neurons": 32, "num_hidden": 3, "activation_fn": "<function relu at 0x000001BAC2C4A8B8>", "lr": 0.00014124140190214133}, "time_since_restore": 3.2488698959350586, "timesteps_since_restore": 0, "iterations_since_restore": 5, "trial_id": "e0e28a86", "experiment_tag": "2_activation_fn=<function relu at 0x000001BAC2C4A8B8>,lr=0.00014124,num_hidden=3,num_neurons=32"}
{"loss": 0.0006587880779989064, "accuracy": -63.38634404500925, "time_this_iter_s": 0.3249974250793457, "should_checkpoint": true, "done": false, "timesteps_total": null, "episodes_total": null, "training_iteration": 6, "experiment_id": "6d99919bd69c4af2838902e6b6bbf8d5", "date": "2020-12-22_00-15-49", "timestamp": 1608624949, "time_total_s": 3.5738673210144043, "pid": 52920, "hostname": "DESKTOP-L6D69LH", "node_ip": "192.168.1.102", "config": {"num_neurons": 32, "num_hidden": 3, "activation_fn": "<function relu at 0x000001BAC2C4A8B8>", "lr": 0.00014124140190214133}, "time_since_restore": 3.5738673210144043, "timesteps_since_restore": 0, "iterations_since_restore": 6, "trial_id": "e0e28a86", "experiment_tag": "2_activation_fn=<function relu at 0x000001BAC2C4A8B8>,lr=0.00014124,num_hidden=3,num_neurons=32"}
{"loss": 0.00037649640580639243, "accuracy": -35.79670181107608, "time_this_iter_s": 0.8109979629516602, "should_checkpoint": true, "done": false, "timesteps_total": null, "episodes_total": null, "training_iteration": 7, "experiment_id": "6d99919bd69c4af2838902e6b6bbf8d5", "date": "2020-12-22_00-15-50", "timestamp": 1608624950, "time_total_s": 4.3848652839660645, "pid": 52920, "hostname": "DESKTOP-L6D69LH", "node_ip": "192.168.1.102", "config": {"num_neurons": 32, "num_hidden": 3, "activation_fn": "<function relu at 0x000001BAC2C4A8B8>", "lr": 0.00014124140190214133}, "time_since_restore": 4.3848652839660645, "timesteps_since_restore": 0, "iterations_since_restore": 7, "trial_id": "e0e28a86", "experiment_tag": "2_activation_fn=<function relu at 0x000001BAC2C4A8B8>,lr=0.00014124,num_hidden=3,num_neurons=32"}
{"loss": 0.00019374466501176357, "accuracy": -17.93554623143832, "time_this_iter_s": 0.5509994029998779, "should_checkpoint": true, "done": false, "timesteps_total": null, "episodes_total": null, "training_iteration": 8, "experiment_id": "6d99919bd69c4af2838902e6b6bbf8d5", "date": "2020-12-22_00-15-50", "timestamp": 1608624950, "time_total_s": 4.935864686965942, "pid": 52920, "hostname": "DESKTOP-L6D69LH", "node_ip": "192.168.1.102", "config": {"num_neurons": 32, "num_hidden": 3, "activation_fn": "<function relu at 0x000001BAC2C4A8B8>", "lr": 0.00014124140190214133}, "time_since_restore": 4.935864686965942, "timesteps_since_restore": 0, "iterations_since_restore": 8, "trial_id": "e0e28a86", "experiment_tag": "2_activation_fn=<function relu at 0x000001BAC2C4A8B8>,lr=0.00014124,num_hidden=3,num_neurons=32"}
{"loss": 8.701178012415767e-05, "accuracy": -7.504055516761149, "time_this_iter_s": 1.0580036640167236, "should_checkpoint": true, "done": false, "timesteps_total": null, "episodes_total": null, "training_iteration": 9, "experiment_id": "6d99919bd69c4af2838902e6b6bbf8d5", "date": "2020-12-22_00-15-51", "timestamp": 1608624951, "time_total_s": 5.993868350982666, "pid": 52920, "hostname": "DESKTOP-L6D69LH", "node_ip": "192.168.1.102", "config": {"num_neurons": 32, "num_hidden": 3, "activation_fn": "<function relu at 0x000001BAC2C4A8B8>", "lr": 0.00014124140190214133}, "time_since_restore": 5.993868350982666, "timesteps_since_restore": 0, "iterations_since_restore": 9, "trial_id": "e0e28a86", "experiment_tag": "2_activation_fn=<function relu at 0x000001BAC2C4A8B8>,lr=0.00014124,num_hidden=3,num_neurons=32"}
{"loss": 3.409985583857633e-05, "accuracy": -2.332733165010986, "time_this_iter_s": 1.0285544395446777, "should_checkpoint": true, "done": true, "timesteps_total": null, "episodes_total": null, "training_iteration": 10, "experiment_id": "6d99919bd69c4af2838902e6b6bbf8d5", "date": "2020-12-22_00-15-52", "timestamp": 1608624952, "time_total_s": 7.022422790527344, "pid": 52920, "hostname": "DESKTOP-L6D69LH", "node_ip": "192.168.1.102", "config": {"num_neurons": 32, "num_hidden": 3, "activation_fn": "<function relu at 0x000001BAC2C4A8B8>", "lr": 0.00014124140190214133}, "time_since_restore": 7.022422790527344, "timesteps_since_restore": 0, "iterations_since_restore": 10, "trial_id": "e0e28a86", "experiment_tag": "2_activation_fn=<function relu at 0x000001BAC2C4A8B8>,lr=0.00014124,num_hidden=3,num_neurons=32"}
